fastembed/__init__.py
fastembed/common/__init__.py
fastembed/common/model_management.py
fastembed/common/onnx_model.py
fastembed/common/preprocessor_utils.py
fastembed/common/types.py
fastembed/common/utils.py
fastembed/embedding.py
fastembed/image/__init__.py
fastembed/image/image_embedding.py
fastembed/image/image_embedding_base.py
fastembed/image/onnx_embedding.py
fastembed/image/onnx_image_model.py
fastembed/image/transform/functional.py
fastembed/image/transform/operators.py
fastembed/late_interaction/__init__.py
fastembed/late_interaction/colbert.py
fastembed/late_interaction/jina_colbert.py
fastembed/late_interaction/late_interaction_embedding_base.py
fastembed/late_interaction/late_interaction_text_embedding.py
fastembed/parallel_processor.py
fastembed/rerank/cross_encoder/__init__.py
fastembed/rerank/cross_encoder/onnx_text_cross_encoder.py
fastembed/rerank/cross_encoder/onnx_text_model.py
fastembed/rerank/cross_encoder/text_cross_encoder.py
fastembed/rerank/cross_encoder/text_cross_encoder_base.py
fastembed/sparse/__init__.py
fastembed/sparse/bm25.py
fastembed/sparse/bm25s/__init__.py
fastembed/sparse/bm25s/bm25.py
fastembed/sparse/bm42.py
fastembed/sparse/sparse_embedding_base.py
fastembed/sparse/sparse_text_embedding.py
fastembed/sparse/splade_pp.py
fastembed/sparse/utils/tokenizer.py
fastembed/text/__init__.py
fastembed/text/clip_embedding.py
fastembed/text/multitask_embedding.py
fastembed/text/onnx_embedding.py
fastembed/text/onnx_text_model.py
fastembed/text/pooled_embedding.py
fastembed/text/pooled_normalized_embedding.py
fastembed/text/text_embedding.py
fastembed/text/text_embedding_base.py
itk_bm25s_extended_fastembed-0.1.2.dist-info/LICENSE
itk_bm25s_extended_fastembed-0.1.2.dist-info/METADATA
itk_bm25s_extended_fastembed-0.1.2.dist-info/NOTICE
itk_bm25s_extended_fastembed-0.1.2.dist-info/WHEEL
itk_bm25s_extended_fastembed-0.1.2.dist-info/RECORD
