Metadata-Version: 2.3
Name: ITK-bm25s-extended-fastembed
Version: 0.1.2
Summary: Fork from fastembed extended with BM25s for sparse embeddings. From fastembed: Fast, light, accurate library built for retrieval embedding generation
License: Apache License
Keywords: vector,embedding,neural,search,qdrant,sentence-transformers,bm25s
Author: Daniel Andreasen
Author-email: akda@aarhus.dk
Requires-Python: >=3.9.0
Classifier: License :: Other/Proprietary License
Classifier: Programming Language :: Python :: 3
Classifier: Programming Language :: Python :: 3.9
Classifier: Programming Language :: Python :: 3.10
Classifier: Programming Language :: Python :: 3.11
Classifier: Programming Language :: Python :: 3.12
Classifier: Programming Language :: Python :: 3.13
Requires-Dist: bm25s (>=0.2.8)
Requires-Dist: huggingface-hub (>=0.20,<1.0)
Requires-Dist: loguru (>=0.7.2,<0.8.0)
Requires-Dist: mmh3 (>=4.1.0,<5.0.0)
Requires-Dist: numpy (>=1.21) ; python_version >= "3.10" and python_version < "3.12"
Requires-Dist: numpy (>=1.21,<2.1.0) ; python_version < "3.10"
Requires-Dist: numpy (>=1.26) ; python_version == "3.12"
Requires-Dist: numpy (>=2.1.0) ; python_version >= "3.13"
Requires-Dist: onnxruntime (>1.20.0) ; python_version >= "3.13"
Requires-Dist: onnxruntime (>=1.17.0,!=1.20.0) ; python_version >= "3.10" and python_version < "3.13"
Requires-Dist: onnxruntime (>=1.17.0,<1.20.0) ; python_version < "3.10"
Requires-Dist: pillow (>=10.3.0,<12.0.0)
Requires-Dist: py-rust-stemmers (>=0.1.0,<0.2.0)
Requires-Dist: requests (>=2.31,<3.0)
Requires-Dist: tokenizers (>=0.15,<1.0)
Requires-Dist: tqdm (>=4.66,<5.0)
Project-URL: Homepage, https://github.com/DKAndreasen/fastembed
Project-URL: Repository, https://github.com/DKAndreasen/fastembed
